pants_backend_bitwarden/__init__.py
pants_backend_bitwarden/goals/decrypt.py
pants_backend_bitwarden/register.py
pants_backend_bitwarden/subsystem.py
pants_backend_bitwarden/targets.py
pants_backend_bitwarden/util_rules/secret.py
pants_backend_bitwarden-0.5.0.dist-info/WHEEL
pants_backend_bitwarden-0.5.0.dist-info/METADATA
pants_backend_bitwarden-0.5.0.dist-info/licenses/LICENSE-MIT.txt
pants_backend_bitwarden-0.5.0.dist-info/RECORD
