Metadata-Version: 2.1
Name: pants_backend_bitwarden
Version: 0.5.0
Summary: A Bitwarden plugin for the Pants build system
Keywords: pantsbuild,pants,backend,bitwarden
Author-email: Tom Solberg <me@sbg.dev>
Classifier: Development Status :: 4 - Beta
Classifier: Programming Language :: Python
Classifier: Topic :: Software Development :: Build Tools
Requires-Dist: pants_backend_secrets>=0.4.0
Project-URL: Changelog, https://github.com/tgolsson/pants-backends/tree/main/pants-plugins/bitwarden/CHANGELOG.md
Project-URL: Code, https://github.com/tgolsson/pants-backends/tree/main/pants-plugins/bitwarden
Project-URL: Repository, https://github.com/tgolsson/pants-backends
